jkUnicode/__init__.py
jkUnicode/_version.py
jkUnicode/aglfn.py
jkUnicode/aglfnData.py
jkUnicode/orthography.py
jkUnicode/py.typed
jkUnicode/uniBlock.py
jkUnicode/uniBlockData.py
jkUnicode/uniCase.py
jkUnicode/uniCat.py
jkUnicode/uniDecomposition.py
jkUnicode/uniName.py
jkUnicode/uniNiceName.py
jkUnicode/uniRangesBits.py
jkUnicode/uniScript.py
jkUnicode/uniScriptData.py
jkUnicode/cmdline/__init__.py
jkUnicode/cmdline/ortho.py
jkUnicode/cmdline/uniinfo.py
jkUnicode/json/ignored_characters.json
jkUnicode/json/ignored_languages.json
jkUnicode/json/language_characters.json
jkUnicode/json/language_characters_hyperglot.json
jkUnicode/json/language_speakers.json
jkUnicode/json/languages.json
jkUnicode/json/languages_additional.json
jkUnicode/json/override_names.json
jkUnicode/json/scripts.json
jkUnicode/json/tags.json
jkUnicode/json/territories.json
jkUnicode/json/languages/_readme.txt
jkUnicode/json/languages/aa.json
jkUnicode/json/languages/ab.json
jkUnicode/json/languages/af.json
jkUnicode/json/languages/agq.json
jkUnicode/json/languages/ak.json
jkUnicode/json/languages/am.json
jkUnicode/json/languages/an.json
jkUnicode/json/languages/ann.json
jkUnicode/json/languages/ar.json
jkUnicode/json/languages/arn.json
jkUnicode/json/languages/as.json
jkUnicode/json/languages/asa.json
jkUnicode/json/languages/ast.json
jkUnicode/json/languages/az.json
jkUnicode/json/languages/ba.json
jkUnicode/json/languages/bal.json
jkUnicode/json/languages/bas.json
jkUnicode/json/languages/be.json
jkUnicode/json/languages/bem.json
jkUnicode/json/languages/bew.json
jkUnicode/json/languages/bez.json
jkUnicode/json/languages/bg.json
jkUnicode/json/languages/bgc.json
jkUnicode/json/languages/bgn.json
jkUnicode/json/languages/bho.json
jkUnicode/json/languages/blo.json
jkUnicode/json/languages/blt.json
jkUnicode/json/languages/bm.json
jkUnicode/json/languages/bn.json
jkUnicode/json/languages/bo.json
jkUnicode/json/languages/br.json
jkUnicode/json/languages/brx.json
jkUnicode/json/languages/bs.json
jkunicode-2.4.0.dist-info/licenses/LICENSE
jkunicode-2.4.0.dist-info/METADATA
jkunicode-2.4.0.dist-info/WHEEL
jkunicode-2.4.0.dist-info/entry_points.txt
jkunicode-2.4.0.dist-info/top_level.txt
jkunicode-2.4.0.dist-info/RECORD
