Metadata-Version: 2.4
Name: jkUnicode
Version: 2.4.0
Summary: Unicode support libraries
Author-email: Jens Kutílek <webmail@kutilek.de>
License-Expression: MIT
Project-URL: Homepage, https://github.com/jenskutilek/jkUnicode
Project-URL: Documentation, https://jkunicode.readthedocs.io/en/latest/
Project-URL: Bug Tracker, https://github.com/jenskutilek/jkUnicode/issues
Project-URL: Changelog, https://github.com/jenskutilek/jkUnicode/blob/master/CHANGELOG.md
Classifier: Environment :: Console
Classifier: Operating System :: OS Independent
Classifier: Programming Language :: Python
Classifier: Programming Language :: Python :: 3 :: Only
Classifier: Programming Language :: Python :: 3.10
Classifier: Programming Language :: Python :: 3.11
Classifier: Programming Language :: Python :: 3.12
Classifier: Programming Language :: Python :: 3.13
Classifier: Programming Language :: Python :: 3.14
Requires-Python: >=3.10
License-File: LICENSE
Provides-Extra: sfnt
Requires-Dist: fonttools>=4.60.2; extra == "sfnt"
Provides-Extra: woff
Requires-Dist: fonttools[woff]>=4.60.2; extra == "woff"
Provides-Extra: all
Requires-Dist: jkUnicode[sfnt]; extra == "all"
Requires-Dist: jkUnicode[woff]; extra == "all"
Provides-Extra: test
Requires-Dist: coverage; extra == "test"
Requires-Dist: flake8; extra == "test"
Requires-Dist: pytest; extra == "test"
Requires-Dist: ruff; extra == "test"
Provides-Extra: dev
Requires-Dist: hyperglot>=0.7.2; extra == "dev"
Requires-Dist: build; extra == "dev"
Requires-Dist: flake8; extra == "dev"
Requires-Dist: wheel; extra == "dev"
Requires-Dist: ruff; extra == "dev"
Requires-Dist: setuptools-scm[toml]; extra == "dev"
Dynamic: license-file
